notion_wrapped/__init__.py
notion_wrapped/analytics.py
notion_wrapped/notion_client.py
notion_wrapped/notion_wrapped.py
notion_wrapped/recurse.py
notion_wrapped/utils.py
notion_wrapped-0.1.5.dist-info/METADATA
notion_wrapped-0.1.5.dist-info/WHEEL
notion_wrapped-0.1.5.dist-info/entry_points.txt
notion_wrapped-0.1.5.dist-info/top_level.txt
notion_wrapped-0.1.5.dist-info/RECORD
