Metadata-Version: 2.1
Name: notion-wrapped
Version: 0.1.5
Summary: A tool to recursively process your Notion workspace to produce plots and analytics
Author-email: Jesse Gilbert <jessegilbert6902@gmail.com>
Project-URL: Homepage, https://github.com/jesenator/notion-wrapped
Classifier: Programming Language :: Python :: 3
Classifier: License :: OSI Approved :: MIT License
Classifier: Operating System :: OS Independent
Requires-Python: >=3.6
Requires-Dist: asttokens==2.4.1
Requires-Dist: certifi==2024.8.30
Requires-Dist: charset-normalizer==3.4.0
Requires-Dist: click==8.1.7
Requires-Dist: contourpy==1.3.1
Requires-Dist: cycler==0.12.1
Requires-Dist: decorator==5.1.1
Requires-Dist: executing==2.1.0
Requires-Dist: fonttools==4.55.0
Requires-Dist: idna==3.10
Requires-Dist: ipython==8.29.0
Requires-Dist: jedi==0.19.2
Requires-Dist: Jinja2==3.1.4
Requires-Dist: joblib==1.4.2
Requires-Dist: jsonpickle==4.0.0
Requires-Dist: kiwisolver==1.4.7
Requires-Dist: MarkupSafe==3.0.2
Requires-Dist: matplotlib==3.9.2
Requires-Dist: matplotlib-inline==0.1.7
Requires-Dist: networkx==3.4.2
Requires-Dist: nltk==3.9.1
Requires-Dist: numpy==2.1.3
Requires-Dist: packaging==24.2
Requires-Dist: parso==0.8.4
Requires-Dist: pexpect==4.9.0
Requires-Dist: pillow==11.0.0
Requires-Dist: prompt_toolkit==3.0.48
Requires-Dist: ptyprocess==0.7.0
Requires-Dist: pure_eval==0.2.3
Requires-Dist: Pygments==2.18.0
Requires-Dist: pyparsing==3.2.0
Requires-Dist: python-dateutil==2.9.0.post0
Requires-Dist: pyvis==0.3.2
Requires-Dist: regex==2024.11.6
Requires-Dist: requests==2.32.3
Requires-Dist: six==1.16.0
Requires-Dist: stack-data==0.6.3
Requires-Dist: tqdm==4.67.0
Requires-Dist: traitlets==5.14.3
Requires-Dist: urllib3==2.2.3
Requires-Dist: wakepy==0.10.1
Requires-Dist: wcwidth==0.2.13
Requires-Dist: wordcloud==1.9.4
